README.md
setup.cfg
setup.py
mern/__init__.py
mern/outlier.py
mern/recommendation.py
mern.egg-info/PKG-INFO
mern.egg-info/SOURCES.txt
mern.egg-info/dependency_links.txt
mern.egg-info/requires.txt
mern.egg-info/top_level.txt