Metadata-Version: 2.1
Name: mern
Version: 0.5
Summary: data pre-processing library
Home-page: https://github.com/bluenet-analytica/mern
Author: mrxxx04
Author-email: rizkimaulana348@gmail.com
License: MIT
Download-URL: https://github.com/bluenet-analytica/mern/archive/v.0.1.zip
Keywords: machine-learning,surpervied-learning,artificial-intelegence
Platform: UNKNOWN
Classifier: Development Status :: 3 - Alpha
Classifier: Intended Audience :: Developers
Classifier: Topic :: Software Development :: Build Tools
Classifier: License :: OSI Approved :: MIT License
Classifier: Programming Language :: Python :: 3
Classifier: Programming Language :: Python :: 3.4
Classifier: Programming Language :: Python :: 3.5
Classifier: Programming Language :: Python :: 3.6
